<?xml version="1.0" encoding="utf-8"?>
<Maps>
    <Map Type="System" Name="WAHP_RW10" Priority="3" Center="-07.4625+109.4217">
        <Runway Name="10">
            <Threshold Name="10" Position="-07.4595+109.4072" ExtendedCentrelineTrack="283" ExtendedCentrelineLength="12" ExtendedCentrelineWidth="1" ExtendedCentrelineTickInterval="1" />
            <Threshold Name="28" Position="-07.4630+109.4212" />
        </Runway>
        <Runway Name="28">
            <Threshold Name="28" Position="-07.4630+109.4212" ExtendedCentrelineTrack="103" ExtendedCentrelineLength="12" ExtendedCentrelineWidth="1" ExtendedCentrelineTickInterval="1" />
            <Threshold Name="10" Position="-07.4595+109.4072" />
        </Runway>
        <!--SID: BND1E, Runway: 10-->
        <Line Pattern="Dotted">-07.4595+109.4072/ESLAP/IDGOS/APONA/DUBIG/SUSVI/DOVUS/REGIP/BND</Line>
        <!--SID: CA1F, Runway: 10-->
        <Line Pattern="Dotted">-07.4595+109.4072/ESLAP/IDGOS/APONA/DUBIG/SUSVI/DOVUS/ATBOX/CA</Line>
        <!--SID: LILP1F, Runway: 10-->
        <Line Pattern="Dotted">-07.4595+109.4072/ESLAP/IDGOS/APONA/KALDU/BIBIA/LILPO</Line>
        <!--STAR: BND1G, Runway: 10-->
        <Line Pattern="Dashed">BND/UDOPI/PAGTO/UPRAS</Line>
        <!--STAR: CA1H, Runway: 10-->
        <Line Pattern="Dashed">CA/MALAM/PAGTO/UPRAS</Line>
        <!--STAR: LILP1H, Runway: 10-->
        <Line Pattern="Dashed">LILPO/SAPON/REGON/UPRAS</Line>
        <Symbol Type="SolidTriangle">
            <Point>ESLAP</Point>
            <Point>LILPO</Point>
            <Point>SUSVI</Point>
            <Point>PAGTO</Point>
            <Point>DUBIG</Point>
            <Point>BND</Point>
            <Point>IDGOS</Point>
            <Point>UDOPI</Point>
            <Point>BIBIA</Point>
            <Point>ATBOX</Point>
            <Point>UPRAS</Point>
            <Point>REGON</Point>
            <Point>KALDU</Point>
            <Point>REGIP</Point>
            <Point>MALAM</Point>
            <Point>DOVUS</Point>
            <Point>APONA</Point>
            <Point>CA</Point>
            <Point>SAPON</Point>
        </Symbol>
    </Map>
    <Map Type="System" Priority="3" Center="-07.4625+109.4217" Name="WAHP_RW10_NAMES">
        <Label>
            <Point>ESLAP</Point>
            <Point>LILPO</Point>
            <Point>SUSVI</Point>
            <Point>PAGTO</Point>
            <Point>DUBIG</Point>
            <Point>BND</Point>
            <Point>IDGOS</Point>
            <Point>UDOPI</Point>
            <Point>BIBIA</Point>
            <Point>ATBOX</Point>
            <Point>UPRAS</Point>
            <Point>REGON</Point>
            <Point>KALDU</Point>
            <Point>REGIP</Point>
            <Point>MALAM</Point>
            <Point>DOVUS</Point>
            <Point>APONA</Point>
            <Point>CA</Point>
            <Point>SAPON</Point>
        </Label>
    </Map>
</Maps>